mdb_codegen/__init__.py
mdb_codegen/data_loader.py
mdb_codegen/djaccess.py
mdb_codegen/jsontools.py
mdb_codegen/mdb-codegen.py
mdb_codegen/mdbtools.py
mdb_codegen-0.1.11.dist-info/METADATA
mdb_codegen-0.1.11.dist-info/WHEEL
mdb_codegen-0.1.11.dist-info/RECORD
