Metadata-Version: 2.1
Name: mdb-codegen
Version: 0.1.11
Summary: 
Author: Josh Brooks
Author-email: josh@catalpa.io
Requires-Python: >=3.8,<4.0
Classifier: Programming Language :: Python :: 3
Classifier: Programming Language :: Python :: 3.8
Classifier: Programming Language :: Python :: 3.9
Classifier: Programming Language :: Python :: 3.10
Classifier: Programming Language :: Python :: 3.11
Requires-Dist: pydantic (>=1.10.2,<2.0.0)
Requires-Dist: pytz (>=2022.6,<2023.0)
Requires-Dist: rich (>=12.6.0,<13.0.0)
